py_sr25519_bindings-0.2.2.dist-info/METADATA
py_sr25519_bindings-0.2.2.dist-info/WHEEL
py_sr25519_bindings-0.2.2.dist-info/licenses/LICENSE
sr25519/__init__.py
sr25519/sr25519.cpython-310-arm-linux-gnueabihf.so
py_sr25519_bindings-0.2.2.dist-info/RECORD
