Metadata-Version: 2.4
Name: py-sr25519-bindings
Version: 0.2.2
Classifier: License :: OSI Approved :: Apache Software License
Classifier: Intended Audience :: Developers
Classifier: Programming Language :: Python :: 3
Classifier: Programming Language :: Python :: 3.7
Classifier: Programming Language :: Python :: 3.8
Classifier: Programming Language :: Python :: 3.9
Classifier: Programming Language :: Python :: 3.10
Classifier: Programming Language :: Python :: 3.11
Classifier: Programming Language :: Python :: 3.12
Classifier: Programming Language :: Python :: 3.13
License-File: LICENSE
Summary: Python bindings for schnorrkel RUST crate
Home-Page: https://github.com/polkascan/py-sr25519-bindings
Author: Polkascan Foundation
Author-email: info@polkascan.org
Maintainer-email: Polkascan Foundation <info@polkascan.org>
License: Apache-2.0
Requires-Python: >=3.7
Project-URL: repository, https://github.com/polkascan/py-sr25519-bindings
Project-URL: homepage, https://github.com/polkascan/py-sr25519-bindings
